agentsoup/__init__.py
agentsoup-0.1.0.dist-info/METADATA
agentsoup-0.1.0.dist-info/WHEEL
agentsoup-0.1.0.dist-info/top_level.txt
agentsoup-0.1.0.dist-info/RECORD
