Metadata-Version: 2.4
Name: agentsoup
Version: 0.1.0
Summary: Mix prompts, models, and logic — cook up LLM-powered functions with ease.
Author-email: Sruly Rosenblat <SrulyRosenblat@gmail.com>
License: MIT
Project-URL: Homepage, https://github.com/SrulyRosenblat/AgentSoup
Requires-Python: >=3.8
Requires-Dist: litellm
Requires-Dist: pydantic
